scodec/__init__.py
scodec/__main__.py
scodec/__version__.py
scodec/codec/__init__.py
scodec/codec/base.py
scodec/codec/n2.py
scodec/codec/n3.py
scodec/config/log.yaml
scodec/logs/__init__.py
scodec/logs/config.py
scodec/logs/config.yaml
scodec/plt/__init__.py
scodec/plt/visualizer.py
scodec-0.0.5.dist-info/LICENSE
scodec-0.0.5.dist-info/METADATA
scodec-0.0.5.dist-info/WHEEL
scodec-0.0.5.dist-info/top_level.txt
scodec-0.0.5.dist-info/RECORD
