Metadata-Version: 2.1
Name: scodec
Version: 0.0.5
Summary: Spatial encoding algorithm using psuedo hilbert curves
Home-page: https://leapsystems.online
Author: cSDes1gn
Author-email: christian@leapsystems.online
License: UNKNOWN
Download-URL: https://github.com/Incuvers/iris-stage/archive/0.0.1.tar.gz
Platform: UNKNOWN
Classifier: Development Status :: 3 - Alpha
Classifier: Topic :: Security :: Cryptography
Classifier: Topic :: Software Development :: Libraries :: Python Modules
Classifier: License :: OSI Approved :: GNU General Public License v3 (GPLv3)
Requires-Python: >=3.7.0
Requires-Dist: Cython
Requires-Dist: matplotlib
Requires-Dist: numpy
Requires-Dist: PyYaml
